Metadata-Version: 1.1
Name: Pytess
Version: 0.1.0
Summary: Pure Python tessellation of points into polygons, including Delauney/Thiessin, and Voronoi polygons.
Home-page: http://github.com/karimbahgat/Pytess
Author: Karim Bahgat
Author-email: karim.bahgat.norway@gmail.com
License: MIT
Keywords: GIS spatial tesselation voronoi delauney triangulation
Platform: UNKNOWN
Classifier: License :: OSI Approved
Classifier: Programming Language :: Python
Classifier: Development Status :: 4 - Beta
Classifier: Intended Audience :: Developers
Classifier: Intended Audience :: Science/Research
Classifier: Intended Audience :: End Users/Desktop
Classifier: Topic :: Scientific/Engineering :: GIS
